pygwin2/__init__.py
pygwin2/color.py
pygwin2/console.py
pygwin2/font.py
pygwin2/gamepad.py
pygwin2/image.py
pygwin2/keyboard.py
pygwin2/mixer.py
pygwin2/mouse.py
pygwin2/pygame.py
pygwin2/rect.py
pygwin2/surface.py
pygwin2/tray.py
pygwin2/window.py
pygwin2/ui/__init__.py
pygwin2/ui/base.py
pygwin2/ui/widget/__init__.py
pygwin2/ui/widget/button.py
pygwin2/ui/widget/checkbox.py
pygwin2/ui/widget/combobox.py
pygwin2/ui/widget/entry.py
pygwin2/ui/widget/image.py
pygwin2/ui/widget/keyselect.py
pygwin2/ui/widget/label.py
pygwin2/ui/widget/loadingbar.py
pygwin2/ui/widget/slider.py
pygwin2/ui/widget/textarea.py
pygwin2/ui/widget/tip.py
pygwin2-2.0.1.dist-info/licenses/LICENSE
pygwin2-2.0.1.dist-info/METADATA
pygwin2-2.0.1.dist-info/WHEEL
pygwin2-2.0.1.dist-info/top_level.txt
pygwin2-2.0.1.dist-info/RECORD
