Metadata-Version: 2.4
Name: pygwin2
Version: 2.0.1
Summary: A library for creating GUI-applications on pygame.
Author-email: MeexReay <meexreay@gmail.com>
License-Expression: WTFPL
Project-URL: Homepage, https://github.com/MeexReay/pygwin2
Project-URL: Issues, https://github.com/MeexReay/pygwin2/issues
Keywords: gui,pygame,windows
Classifier: Programming Language :: Python :: 3
Classifier: Operating System :: OS Independent
Requires-Python: >=3.7
License-File: LICENSE
Requires-Dist: pydub
Requires-Dist: pygame
Requires-Dist: pyautogui
Requires-Dist: inputs
Requires-Dist: pillow
Requires-Dist: wxPython
Requires-Dist: randstr
Dynamic: license-file
